media_widget-0.1.0.dist-info/licenses/LICENSE
mediawidget/__init__.py
mediawidget/app.py
mediawidget/icons/__init__.py
mediawidget/icons/next.png
mediawidget/icons/pause.png
mediawidget/icons/play.png
mediawidget/icons/prev.png
media_widget-0.1.0.dist-info/METADATA
media_widget-0.1.0.dist-info/WHEEL
media_widget-0.1.0.dist-info/entry_points.txt
media_widget-0.1.0.dist-info/top_level.txt
media_widget-0.1.0.dist-info/RECORD
