Metadata-Version: 2.4
Name: media-widget
Version: 0.1.0
Summary: Lightweight Miniplayer compatible with media running in Windows/Browser and Taskbar control of media.
Author-email: Jaskaran Bhogal <jaskaran197@gmail.com>
License: MIT License
Requires-Python: ==3.9.*
License-File: LICENSE
Requires-Dist: pystray
Requires-Dist: Pillow
Requires-Dist: winrt
Dynamic: license-file
